docs/source/conf.py
ldcoolp_figshare/__init__.py
ldcoolp_figshare/main.py
ldcoolp_figshare-0.3.2.dist-info/LICENSE
ldcoolp_figshare-0.3.2.dist-info/METADATA
ldcoolp_figshare-0.3.2.dist-info/WHEEL
ldcoolp_figshare-0.3.2.dist-info/top_level.txt
ldcoolp_figshare-0.3.2.dist-info/RECORD
