Metadata-Version: 2.1
Name: ldcoolp-figshare
Version: 0.3.2
Summary: Python tool using the Figshare API for data curation
Home-page: https://github.com/UAL-RE/ldcoolp-figshare/
Author: Chun Ly
Author-email: astro.chun@gmail.com
License: MIT License
Project-URL: Source, https://github.com/UAL-RE/ldcoolp-figshare/
Project-URL: Documentation, https://ldcoolp-figshare.readthedocs.io/
Project-URL: Tracker, https://github.com/UAL-RE/ldcoolp-figshare/issues
Platform: UNKNOWN
Classifier: Development Status :: 4 - Beta
Classifier: Programming Language :: Python :: 3 :: Only
Classifier: Programming Language :: Python :: 3.7
Classifier: Programming Language :: Python :: 3.8
Classifier: Programming Language :: Python :: 3.9
Requires-Python: >=3.7
License-File: LICENSE
Requires-Dist: redata (==0.4.1)
